ncloud_server/__init__.py
ncloud_server/api_client.py
ncloud_server/configuration.py
ncloud_server/rest.py
ncloud_server/api/__init__.py
ncloud_server/api/v2_api.py
ncloud_server/model/__init__.py
ncloud_server/model/access_control_group.py
ncloud_server/model/access_control_rule.py
ncloud_server/model/add_nas_volume_access_control_request.py
ncloud_server/model/add_nas_volume_access_control_response.py
ncloud_server/model/add_port_forwarding_rules_request.py
ncloud_server/model/add_port_forwarding_rules_response.py
ncloud_server/model/associate_public_ip_with_server_instance_request.py
ncloud_server/model/associate_public_ip_with_server_instance_response.py
ncloud_server/model/attach_block_storage_instance_request.py
ncloud_server/model/attach_block_storage_instance_response.py
ncloud_server/model/attach_network_interface_request.py
ncloud_server/model/attach_network_interface_response.py
ncloud_server/model/block_storage_instance.py
ncloud_server/model/block_storage_snapshot_instance.py
ncloud_server/model/change_block_storage_volume_size_request.py
ncloud_server/model/change_block_storage_volume_size_response.py
ncloud_server/model/change_nas_volume_size_request.py
ncloud_server/model/change_nas_volume_size_response.py
ncloud_server/model/change_server_instance_spec_request.py
ncloud_server/model/change_server_instance_spec_response.py
ncloud_server/model/common_code.py
ncloud_server/model/create_block_storage_instance_request.py
ncloud_server/model/create_block_storage_instance_response.py
ncloud_server/model/create_block_storage_snapshot_instance_request.py
ncloud_server/model/create_block_storage_snapshot_instance_response.py
ncloud_server/model/create_instance_tags_request.py
ncloud_server/model/create_instance_tags_response.py
ncloud_server/model/create_login_key_request.py
ncloud_server/model/create_login_key_response.py
ncloud_server/model/create_member_server_image_request.py
ncloud_server/model/create_member_server_image_response.py
ncloud_server-1.1.2.dist-info/LICENSE
ncloud_server-1.1.2.dist-info/METADATA
ncloud_server-1.1.2.dist-info/WHEEL
ncloud_server-1.1.2.dist-info/top_level.txt
ncloud_server-1.1.2.dist-info/RECORD
